<?xml version="1.0" encoding="utf-8"?>
<TextureAtlas imagePath="nuzzus-cool.png">
	<!-- Created with Adobe Animate version 23.0.2.103 -->
	<!-- http://www.adobe.com/products/animate.html -->
	<SubTexture name="cool background_gif0000" x="0" y="0" width="256" height="224"/>
	<SubTexture name="cool background_gif0001" x="0" y="0" width="256" height="224"/>
	<SubTexture name="cool background_gif0002" x="0" y="0" width="256" height="224"/>
	<SubTexture name="cool background_gif0003" x="256" y="0" width="256" height="224"/>
	<SubTexture name="cool background_gif0004" x="256" y="0" width="256" height="224"/>
	<SubTexture name="cool background_gif0005" x="256" y="0" width="256" height="224"/>
	<SubTexture name="cool background_gif0006" x="512" y="0" width="256" height="224"/>
	<SubTexture name="cool background_gif0007" x="512" y="0" width="256" height="224"/>
	<SubTexture name="cool background_gif0008" x="512" y="0" width="256" height="224"/>
	<SubTexture name="cool background_gif0009" x="768" y="0" width="256" height="224"/>
	<SubTexture name="cool background_gif0010" x="768" y="0" width="256" height="224"/>
	<SubTexture name="cool background_gif0011" x="768" y="0" width="256" height="224"/>
	<SubTexture name="cool background_gif0012" x="1024" y="0" width="256" height="224"/>
	<SubTexture name="cool background_gif0013" x="1024" y="0" width="256" height="224"/>
	<SubTexture name="cool background_gif0014" x="1024" y="0" width="256" height="224"/>
	<SubTexture name="cool background_gif0015" x="1280" y="0" width="256" height="224"/>
	<SubTexture name="cool background_gif0016" x="1280" y="0" width="256" height="224"/>
	<SubTexture name="cool background_gif0017" x="1280" y="0" width="256" height="224"/>
	<SubTexture name="cool background_gif0018" x="1536" y="0" width="256" height="224"/>
	<SubTexture name="cool background_gif0019" x="1536" y="0" width="256" height="224"/>
	<SubTexture name="cool background_gif0020" x="1536" y="0" width="256" height="224"/>
	<SubTexture name="cool background_gif0021" x="1792" y="0" width="256" height="224"/>
	<SubTexture name="cool background_gif0022" x="1792" y="0" width="256" height="224"/>
	<SubTexture name="cool background_gif0023" x="1792" y="0" width="256" height="224"/>
	<SubTexture name="cool background_gif0024" x="2048" y="0" width="256" height="224"/>
	<SubTexture name="cool background_gif0025" x="2048" y="0" width="256" height="224"/>
	<SubTexture name="cool background_gif0026" x="2048" y="0" width="256" height="224"/>
	<SubTexture name="cool background_gif0027" x="2304" y="0" width="256" height="224"/>
	<SubTexture name="cool background_gif0028" x="2304" y="0" width="256" height="224"/>
	<SubTexture name="cool background_gif0029" x="2304" y="0" width="256" height="224"/>
	<SubTexture name="cool background_gif0030" x="2560" y="0" width="256" height="224"/>
	<SubTexture name="cool background_gif0031" x="2560" y="0" width="256" height="224"/>
	<SubTexture name="cool background_gif0032" x="2560" y="0" width="256" height="224"/>
	<SubTexture name="cool background_gif0033" x="2816" y="0" width="256" height="224"/>
	<SubTexture name="cool background_gif0034" x="2816" y="0" width="256" height="224"/>
	<SubTexture name="cool background_gif0035" x="2816" y="0" width="256" height="224"/>
	<SubTexture name="cool background_gif0036" x="3072" y="0" width="256" height="224"/>
	<SubTexture name="cool background_gif0037" x="3072" y="0" width="256" height="224"/>
	<SubTexture name="cool background_gif0038" x="3072" y="0" width="256" height="224"/>
	<SubTexture name="cool background_gif0039" x="3328" y="0" width="256" height="224"/>
	<SubTexture name="cool background_gif0040" x="3328" y="0" width="256" height="224"/>
	<SubTexture name="cool background_gif0041" x="3328" y="0" width="256" height="224"/>
	<SubTexture name="cool background_gif0042" x="3584" y="0" width="256" height="224"/>
	<SubTexture name="cool background_gif0043" x="3584" y="0" width="256" height="224"/>
	<SubTexture name="cool background_gif0044" x="3584" y="0" width="256" height="224"/>
	<SubTexture name="cool background_gif0045" x="3840" y="0" width="256" height="224"/>
	<SubTexture name="cool background_gif0046" x="3840" y="0" width="256" height="224"/>
	<SubTexture name="cool background_gif0047" x="3840" y="0" width="256" height="224"/>
	<SubTexture name="cool background_gif0048" x="0" y="224" width="256" height="224"/>
	<SubTexture name="cool background_gif0049" x="0" y="224" width="256" height="224"/>
	<SubTexture name="cool background_gif0050" x="0" y="224" width="256" height="224"/>
	<SubTexture name="cool background_gif0051" x="256" y="224" width="256" height="224"/>
	<SubTexture name="cool background_gif0052" x="256" y="224" width="256" height="224"/>
	<SubTexture name="cool background_gif0053" x="256" y="224" width="256" height="224"/>
	<SubTexture name="cool background_gif0054" x="512" y="224" width="256" height="224"/>
	<SubTexture name="cool background_gif0055" x="512" y="224" width="256" height="224"/>
	<SubTexture name="cool background_gif0056" x="512" y="224" width="256" height="224"/>
	<SubTexture name="cool background_gif0057" x="768" y="224" width="256" height="224"/>
	<SubTexture name="cool background_gif0058" x="768" y="224" width="256" height="224"/>
	<SubTexture name="cool background_gif0059" x="768" y="224" width="256" height="224"/>
	<SubTexture name="cool background_gif0060" x="1024" y="224" width="256" height="224"/>
	<SubTexture name="cool background_gif0061" x="1024" y="224" width="256" height="224"/>
	<SubTexture name="cool background_gif0062" x="1024" y="224" width="256" height="224"/>
	<SubTexture name="cool background_gif0063" x="1280" y="224" width="256" height="224"/>
	<SubTexture name="cool background_gif0064" x="1280" y="224" width="256" height="224"/>
	<SubTexture name="cool background_gif0065" x="1280" y="224" width="256" height="224"/>
	<SubTexture name="cool background_gif0066" x="1536" y="224" width="256" height="224"/>
	<SubTexture name="cool background_gif0067" x="1536" y="224" width="256" height="224"/>
	<SubTexture name="cool background_gif0068" x="1536" y="224" width="256" height="224"/>
	<SubTexture name="cool background_gif0069" x="1792" y="224" width="256" height="224"/>
	<SubTexture name="cool background_gif0070" x="1792" y="224" width="256" height="224"/>
	<SubTexture name="cool background_gif0071" x="1792" y="224" width="256" height="224"/>
	<SubTexture name="cool background_gif0072" x="2048" y="224" width="256" height="224"/>
	<SubTexture name="cool background_gif0073" x="2048" y="224" width="256" height="224"/>
	<SubTexture name="cool background_gif0074" x="2048" y="224" width="256" height="224"/>
	<SubTexture name="cool background_gif0075" x="2304" y="224" width="256" height="224"/>
	<SubTexture name="cool background_gif0076" x="2304" y="224" width="256" height="224"/>
	<SubTexture name="cool background_gif0077" x="2304" y="224" width="256" height="224"/>
	<SubTexture name="cool background_gif0078" x="2560" y="224" width="256" height="224"/>
	<SubTexture name="cool background_gif0079" x="2560" y="224" width="256" height="224"/>
	<SubTexture name="cool background_gif0080" x="2560" y="224" width="256" height="224"/>
	<SubTexture name="cool background_gif0081" x="2816" y="224" width="256" height="224"/>
	<SubTexture name="cool background_gif0082" x="2816" y="224" width="256" height="224"/>
	<SubTexture name="cool background_gif0083" x="2816" y="224" width="256" height="224"/>
	<SubTexture name="cool background_gif0084" x="3072" y="224" width="256" height="224"/>
	<SubTexture name="cool background_gif0085" x="3072" y="224" width="256" height="224"/>
	<SubTexture name="cool background_gif0086" x="3072" y="224" width="256" height="224"/>
	<SubTexture name="cool background_gif0087" x="3328" y="224" width="256" height="224"/>
	<SubTexture name="cool background_gif0088" x="3328" y="224" width="256" height="224"/>
	<SubTexture name="cool background_gif0089" x="3328" y="224" width="256" height="224"/>
	<SubTexture name="cool background_gif0090" x="3584" y="224" width="256" height="224"/>
	<SubTexture name="cool background_gif0091" x="3584" y="224" width="256" height="224"/>
	<SubTexture name="cool background_gif0092" x="3584" y="224" width="256" height="224"/>
	<SubTexture name="cool background_gif0093" x="3840" y="224" width="256" height="224"/>
	<SubTexture name="cool background_gif0094" x="3840" y="224" width="256" height="224"/>
	<SubTexture name="cool background_gif0095" x="3840" y="224" width="256" height="224"/>
	<SubTexture name="cool background_gif0096" x="0" y="448" width="256" height="224"/>
	<SubTexture name="cool background_gif0097" x="0" y="448" width="256" height="224"/>
	<SubTexture name="cool background_gif0098" x="0" y="448" width="256" height="224"/>
	<SubTexture name="cool background_gif0099" x="256" y="448" width="256" height="224"/>
	<SubTexture name="cool background_gif0100" x="256" y="448" width="256" height="224"/>
	<SubTexture name="cool background_gif0101" x="256" y="448" width="256" height="224"/>
	<SubTexture name="cool background_gif0102" x="512" y="448" width="256" height="224"/>
	<SubTexture name="cool background_gif0103" x="512" y="448" width="256" height="224"/>
	<SubTexture name="cool background_gif0104" x="512" y="448" width="256" height="224"/>
	<SubTexture name="cool background_gif0105" x="768" y="448" width="256" height="224"/>
	<SubTexture name="cool background_gif0106" x="768" y="448" width="256" height="224"/>
	<SubTexture name="cool background_gif0107" x="768" y="448" width="256" height="224"/>
	<SubTexture name="cool background_gif0108" x="1024" y="448" width="256" height="224"/>
	<SubTexture name="cool background_gif0109" x="1024" y="448" width="256" height="224"/>
	<SubTexture name="cool background_gif0110" x="1024" y="448" width="256" height="224"/>
	<SubTexture name="cool background_gif0111" x="1280" y="448" width="256" height="224"/>
	<SubTexture name="cool background_gif0112" x="1280" y="448" width="256" height="224"/>
	<SubTexture name="cool background_gif0113" x="1280" y="448" width="256" height="224"/>
	<SubTexture name="cool background_gif0114" x="1536" y="448" width="256" height="224"/>
	<SubTexture name="cool background_gif0115" x="1536" y="448" width="256" height="224"/>
	<SubTexture name="cool background_gif0116" x="1536" y="448" width="256" height="224"/>
	<SubTexture name="cool background_gif0117" x="1792" y="448" width="256" height="224"/>
	<SubTexture name="cool background_gif0118" x="1792" y="448" width="256" height="224"/>
	<SubTexture name="cool background_gif0119" x="1792" y="448" width="256" height="224"/>
	<SubTexture name="cool background_gif0120" x="2048" y="448" width="256" height="224"/>
	<SubTexture name="cool background_gif0121" x="2048" y="448" width="256" height="224"/>
	<SubTexture name="cool background_gif0122" x="2048" y="448" width="256" height="224"/>
	<SubTexture name="cool background_gif0123" x="2304" y="448" width="256" height="224"/>
	<SubTexture name="cool background_gif0124" x="2304" y="448" width="256" height="224"/>
	<SubTexture name="cool background_gif0125" x="2304" y="448" width="256" height="224"/>
	<SubTexture name="cool background_gif0126" x="2560" y="448" width="256" height="224"/>
	<SubTexture name="cool background_gif0127" x="2560" y="448" width="256" height="224"/>
	<SubTexture name="cool background_gif0128" x="2560" y="448" width="256" height="224"/>
	<SubTexture name="cool background_gif0129" x="2816" y="448" width="256" height="224"/>
	<SubTexture name="cool background_gif0130" x="2816" y="448" width="256" height="224"/>
	<SubTexture name="cool background_gif0131" x="2816" y="448" width="256" height="224"/>
	<SubTexture name="cool background_gif0132" x="3072" y="448" width="256" height="224"/>
	<SubTexture name="cool background_gif0133" x="3072" y="448" width="256" height="224"/>
	<SubTexture name="cool background_gif0134" x="3072" y="448" width="256" height="224"/>
	<SubTexture name="cool background_gif0135" x="3328" y="448" width="256" height="224"/>
	<SubTexture name="cool background_gif0136" x="3328" y="448" width="256" height="224"/>
	<SubTexture name="cool background_gif0137" x="3328" y="448" width="256" height="224"/>
	<SubTexture name="cool background_gif0138" x="3584" y="448" width="256" height="224"/>
	<SubTexture name="cool background_gif0139" x="3584" y="448" width="256" height="224"/>
	<SubTexture name="cool background_gif0140" x="3584" y="448" width="256" height="224"/>
	<SubTexture name="cool background_gif0141" x="3840" y="448" width="256" height="224"/>
	<SubTexture name="cool background_gif0142" x="3840" y="448" width="256" height="224"/>
	<SubTexture name="cool background_gif0143" x="3840" y="448" width="256" height="224"/>
	<SubTexture name="cool background_gif0144" x="0" y="672" width="256" height="224"/>
	<SubTexture name="cool background_gif0145" x="0" y="672" width="256" height="224"/>
	<SubTexture name="cool background_gif0146" x="0" y="672" width="256" height="224"/>
	<SubTexture name="cool background_gif0147" x="256" y="672" width="256" height="224"/>
	<SubTexture name="cool background_gif0148" x="256" y="672" width="256" height="224"/>
	<SubTexture name="cool background_gif0149" x="256" y="672" width="256" height="224"/>
	<SubTexture name="cool background_gif0150" x="512" y="672" width="256" height="224"/>
	<SubTexture name="cool background_gif0151" x="512" y="672" width="256" height="224"/>
	<SubTexture name="cool background_gif0152" x="512" y="672" width="256" height="224"/>
	<SubTexture name="cool background_gif0153" x="768" y="672" width="256" height="224"/>
	<SubTexture name="cool background_gif0154" x="768" y="672" width="256" height="224"/>
	<SubTexture name="cool background_gif0155" x="768" y="672" width="256" height="224"/>
	<SubTexture name="cool background_gif0156" x="1024" y="672" width="256" height="224"/>
	<SubTexture name="cool background_gif0157" x="1024" y="672" width="256" height="224"/>
	<SubTexture name="cool background_gif0158" x="1024" y="672" width="256" height="224"/>
	<SubTexture name="cool background_gif0159" x="1280" y="672" width="256" height="224"/>
	<SubTexture name="cool background_gif0160" x="1280" y="672" width="256" height="224"/>
	<SubTexture name="cool background_gif0161" x="1280" y="672" width="256" height="224"/>
	<SubTexture name="cool background_gif0162" x="1536" y="672" width="256" height="224"/>
	<SubTexture name="cool background_gif0163" x="1536" y="672" width="256" height="224"/>
	<SubTexture name="cool background_gif0164" x="1536" y="672" width="256" height="224"/>
	<SubTexture name="cool background_gif0165" x="1792" y="672" width="256" height="224"/>
	<SubTexture name="cool background_gif0166" x="1792" y="672" width="256" height="224"/>
	<SubTexture name="cool background_gif0167" x="1792" y="672" width="256" height="224"/>
	<SubTexture name="cool background_gif0168" x="2048" y="672" width="256" height="224"/>
	<SubTexture name="cool background_gif0169" x="2048" y="672" width="256" height="224"/>
	<SubTexture name="cool background_gif0170" x="2048" y="672" width="256" height="224"/>
	<SubTexture name="cool background_gif0171" x="2304" y="672" width="256" height="224"/>
	<SubTexture name="cool background_gif0172" x="2304" y="672" width="256" height="224"/>
	<SubTexture name="cool background_gif0173" x="2304" y="672" width="256" height="224"/>
	<SubTexture name="cool background_gif0174" x="2560" y="672" width="256" height="224"/>
	<SubTexture name="cool background_gif0175" x="2560" y="672" width="256" height="224"/>
	<SubTexture name="cool background_gif0176" x="2560" y="672" width="256" height="224"/>
	<SubTexture name="cool background_gif0177" x="2816" y="672" width="256" height="224"/>
	<SubTexture name="cool background_gif0178" x="2816" y="672" width="256" height="224"/>
	<SubTexture name="cool background_gif0179" x="2816" y="672" width="256" height="224"/>
	<SubTexture name="cool background_gif0180" x="3072" y="672" width="256" height="224"/>
	<SubTexture name="cool background_gif0181" x="3072" y="672" width="256" height="224"/>
	<SubTexture name="cool background_gif0182" x="3072" y="672" width="256" height="224"/>
	<SubTexture name="cool background_gif0183" x="3328" y="672" width="256" height="224"/>
	<SubTexture name="cool background_gif0184" x="3328" y="672" width="256" height="224"/>
	<SubTexture name="cool background_gif0185" x="3328" y="672" width="256" height="224"/>
	<SubTexture name="cool background_gif0186" x="3584" y="672" width="256" height="224"/>
	<SubTexture name="cool background_gif0187" x="3584" y="672" width="256" height="224"/>
	<SubTexture name="cool background_gif0188" x="3584" y="672" width="256" height="224"/>
	<SubTexture name="cool background_gif0189" x="3840" y="672" width="256" height="224"/>
	<SubTexture name="cool background_gif0190" x="3840" y="672" width="256" height="224"/>
	<SubTexture name="cool background_gif0191" x="3840" y="672" width="256" height="224"/>
	<SubTexture name="cool background_gif0192" x="0" y="896" width="256" height="224"/>
	<SubTexture name="cool background_gif0193" x="0" y="896" width="256" height="224"/>
	<SubTexture name="cool background_gif0194" x="0" y="896" width="256" height="224"/>
	<SubTexture name="cool background_gif0195" x="256" y="896" width="256" height="224"/>
	<SubTexture name="cool background_gif0196" x="256" y="896" width="256" height="224"/>
	<SubTexture name="cool background_gif0197" x="256" y="896" width="256" height="224"/>
	<SubTexture name="cool background_gif0198" x="512" y="896" width="256" height="224"/>
	<SubTexture name="cool background_gif0199" x="512" y="896" width="256" height="224"/>
	<SubTexture name="cool background_gif0200" x="512" y="896" width="256" height="224"/>
	<SubTexture name="cool background_gif0201" x="768" y="896" width="256" height="224"/>
	<SubTexture name="cool background_gif0202" x="768" y="896" width="256" height="224"/>
	<SubTexture name="cool background_gif0203" x="768" y="896" width="256" height="224"/>
	<SubTexture name="cool background_gif0204" x="1024" y="896" width="256" height="224"/>
	<SubTexture name="cool background_gif0205" x="1024" y="896" width="256" height="224"/>
	<SubTexture name="cool background_gif0206" x="1024" y="896" width="256" height="224"/>
	<SubTexture name="cool background_gif0207" x="1280" y="896" width="256" height="224"/>
	<SubTexture name="cool background_gif0208" x="1280" y="896" width="256" height="224"/>
	<SubTexture name="cool background_gif0209" x="1280" y="896" width="256" height="224"/>
	<SubTexture name="cool background_gif0210" x="1536" y="896" width="256" height="224"/>
	<SubTexture name="cool background_gif0211" x="1536" y="896" width="256" height="224"/>
	<SubTexture name="cool background_gif0212" x="1536" y="896" width="256" height="224"/>
	<SubTexture name="cool background_gif0213" x="1792" y="896" width="256" height="224"/>
	<SubTexture name="cool background_gif0214" x="1792" y="896" width="256" height="224"/>
	<SubTexture name="cool background_gif0215" x="1792" y="896" width="256" height="224"/>
	<SubTexture name="cool background_gif0216" x="2048" y="896" width="256" height="224"/>
	<SubTexture name="cool background_gif0217" x="2048" y="896" width="256" height="224"/>
	<SubTexture name="cool background_gif0218" x="2048" y="896" width="256" height="224"/>
	<SubTexture name="cool background_gif0219" x="2304" y="896" width="256" height="224"/>
	<SubTexture name="cool background_gif0220" x="2304" y="896" width="256" height="224"/>
	<SubTexture name="cool background_gif0221" x="2304" y="896" width="256" height="224"/>
	<SubTexture name="cool background_gif0222" x="2560" y="896" width="256" height="224"/>
	<SubTexture name="cool background_gif0223" x="2560" y="896" width="256" height="224"/>
	<SubTexture name="cool background_gif0224" x="2560" y="896" width="256" height="224"/>
	<SubTexture name="cool background_gif0225" x="2816" y="896" width="256" height="224"/>
	<SubTexture name="cool background_gif0226" x="2816" y="896" width="256" height="224"/>
	<SubTexture name="cool background_gif0227" x="2816" y="896" width="256" height="224"/>
	<SubTexture name="cool background_gif0228" x="3072" y="896" width="256" height="224"/>
	<SubTexture name="cool background_gif0229" x="3072" y="896" width="256" height="224"/>
	<SubTexture name="cool background_gif0230" x="3072" y="896" width="256" height="224"/>
	<SubTexture name="cool background_gif0231" x="3328" y="896" width="256" height="224"/>
	<SubTexture name="cool background_gif0232" x="3328" y="896" width="256" height="224"/>
	<SubTexture name="cool background_gif0233" x="3328" y="896" width="256" height="224"/>
	<SubTexture name="cool background_gif0234" x="3584" y="896" width="256" height="224"/>
	<SubTexture name="cool background_gif0235" x="3584" y="896" width="256" height="224"/>
	<SubTexture name="cool background_gif0236" x="3584" y="896" width="256" height="224"/>
	<SubTexture name="cool background_gif0237" x="3840" y="896" width="256" height="224"/>
	<SubTexture name="cool background_gif0238" x="3840" y="896" width="256" height="224"/>
	<SubTexture name="cool background_gif0239" x="3840" y="896" width="256" height="224"/>
	<SubTexture name="cool background_gif0240" x="0" y="1120" width="256" height="224"/>
	<SubTexture name="cool background_gif0241" x="0" y="1120" width="256" height="224"/>
	<SubTexture name="cool background_gif0242" x="0" y="1120" width="256" height="224"/>
	<SubTexture name="cool background_gif0243" x="256" y="1120" width="256" height="224"/>
	<SubTexture name="cool background_gif0244" x="256" y="1120" width="256" height="224"/>
	<SubTexture name="cool background_gif0245" x="256" y="1120" width="256" height="224"/>
	<SubTexture name="cool background_gif0246" x="512" y="1120" width="256" height="224"/>
	<SubTexture name="cool background_gif0247" x="512" y="1120" width="256" height="224"/>
	<SubTexture name="cool background_gif0248" x="512" y="1120" width="256" height="224"/>
	<SubTexture name="cool background_gif0249" x="768" y="1120" width="256" height="224"/>
	<SubTexture name="cool background_gif0250" x="768" y="1120" width="256" height="224"/>
	<SubTexture name="cool background_gif0251" x="768" y="1120" width="256" height="224"/>
	<SubTexture name="cool background_gif0252" x="1024" y="1120" width="256" height="224"/>
	<SubTexture name="cool background_gif0253" x="1024" y="1120" width="256" height="224"/>
	<SubTexture name="cool background_gif0254" x="1024" y="1120" width="256" height="224"/>
	<SubTexture name="cool background_gif0255" x="1280" y="1120" width="256" height="224"/>
	<SubTexture name="cool background_gif0256" x="1280" y="1120" width="256" height="224"/>
	<SubTexture name="cool background_gif0257" x="1280" y="1120" width="256" height="224"/>
	<SubTexture name="cool background_gif0258" x="1536" y="1120" width="256" height="224"/>
	<SubTexture name="cool background_gif0259" x="1536" y="1120" width="256" height="224"/>
	<SubTexture name="cool background_gif0260" x="1536" y="1120" width="256" height="224"/>
	<SubTexture name="cool background_gif0261" x="1792" y="1120" width="256" height="224"/>
	<SubTexture name="cool background_gif0262" x="1792" y="1120" width="256" height="224"/>
	<SubTexture name="cool background_gif0263" x="1792" y="1120" width="256" height="224"/>
	<SubTexture name="cool background_gif0264" x="2048" y="1120" width="256" height="224"/>
	<SubTexture name="cool background_gif0265" x="2048" y="1120" width="256" height="224"/>
	<SubTexture name="cool background_gif0266" x="2048" y="1120" width="256" height="224"/>
	<SubTexture name="cool background_gif0267" x="2304" y="1120" width="256" height="224"/>
	<SubTexture name="cool background_gif0268" x="2304" y="1120" width="256" height="224"/>
	<SubTexture name="cool background_gif0269" x="2304" y="1120" width="256" height="224"/>
	<SubTexture name="cool background_gif0270" x="2560" y="1120" width="256" height="224"/>
	<SubTexture name="cool background_gif0271" x="2560" y="1120" width="256" height="224"/>
	<SubTexture name="cool background_gif0272" x="2560" y="1120" width="256" height="224"/>
	<SubTexture name="cool background_gif0273" x="2816" y="1120" width="256" height="224"/>
	<SubTexture name="cool background_gif0274" x="2816" y="1120" width="256" height="224"/>
	<SubTexture name="cool background_gif0275" x="2816" y="1120" width="256" height="224"/>
	<SubTexture name="cool background_gif0276" x="3072" y="1120" width="256" height="224"/>
	<SubTexture name="cool background_gif0277" x="3072" y="1120" width="256" height="224"/>
	<SubTexture name="cool background_gif0278" x="3072" y="1120" width="256" height="224"/>
	<SubTexture name="cool background_gif0279" x="3328" y="1120" width="256" height="224"/>
	<SubTexture name="cool background_gif0280" x="3328" y="1120" width="256" height="224"/>
	<SubTexture name="cool background_gif0281" x="3328" y="1120" width="256" height="224"/>
	<SubTexture name="cool background_gif0282" x="3584" y="1120" width="256" height="224"/>
	<SubTexture name="cool background_gif0283" x="3584" y="1120" width="256" height="224"/>
	<SubTexture name="cool background_gif0284" x="3584" y="1120" width="256" height="224"/>
	<SubTexture name="cool background_gif0285" x="3840" y="1120" width="256" height="224"/>
	<SubTexture name="cool background_gif0286" x="3840" y="1120" width="256" height="224"/>
	<SubTexture name="cool background_gif0287" x="3840" y="1120" width="256" height="224"/>
	<SubTexture name="cool background_gif0288" x="0" y="1344" width="256" height="224"/>
	<SubTexture name="cool background_gif0289" x="0" y="1344" width="256" height="224"/>
	<SubTexture name="cool background_gif0290" x="0" y="1344" width="256" height="224"/>
	<SubTexture name="cool background_gif0291" x="256" y="1344" width="256" height="224"/>
	<SubTexture name="cool background_gif0292" x="256" y="1344" width="256" height="224"/>
	<SubTexture name="cool background_gif0293" x="256" y="1344" width="256" height="224"/>
	<SubTexture name="cool background_gif0294" x="512" y="1344" width="256" height="224"/>
	<SubTexture name="cool background_gif0295" x="512" y="1344" width="256" height="224"/>
	<SubTexture name="cool background_gif0296" x="512" y="1344" width="256" height="224"/>
	<SubTexture name="cool background_gif0297" x="768" y="1344" width="256" height="224"/>
	<SubTexture name="cool background_gif0298" x="768" y="1344" width="256" height="224"/>
	<SubTexture name="cool background_gif0299" x="768" y="1344" width="256" height="224"/>
	<SubTexture name="cool background_gif0300" x="1024" y="1344" width="256" height="224"/>
	<SubTexture name="cool background_gif0301" x="1024" y="1344" width="256" height="224"/>
	<SubTexture name="cool background_gif0302" x="1024" y="1344" width="256" height="224"/>
	<SubTexture name="cool background_gif0303" x="1280" y="1344" width="256" height="224"/>
	<SubTexture name="cool background_gif0304" x="1280" y="1344" width="256" height="224"/>
	<SubTexture name="cool background_gif0305" x="1280" y="1344" width="256" height="224"/>
	<SubTexture name="cool background_gif0306" x="1536" y="1344" width="256" height="224"/>
	<SubTexture name="cool background_gif0307" x="1536" y="1344" width="256" height="224"/>
	<SubTexture name="cool background_gif0308" x="1536" y="1344" width="256" height="224"/>
	<SubTexture name="cool background_gif0309" x="1792" y="1344" width="256" height="224"/>
	<SubTexture name="cool background_gif0310" x="1792" y="1344" width="256" height="224"/>
	<SubTexture name="cool background_gif0311" x="1792" y="1344" width="256" height="224"/>
	<SubTexture name="cool background_gif0312" x="2048" y="1344" width="256" height="224"/>
	<SubTexture name="cool background_gif0313" x="2048" y="1344" width="256" height="224"/>
	<SubTexture name="cool background_gif0314" x="2048" y="1344" width="256" height="224"/>
	<SubTexture name="cool background_gif0315" x="2304" y="1344" width="256" height="224"/>
	<SubTexture name="cool background_gif0316" x="2304" y="1344" width="256" height="224"/>
	<SubTexture name="cool background_gif0317" x="2304" y="1344" width="256" height="224"/>
	<SubTexture name="cool background_gif0318" x="2560" y="1344" width="256" height="224"/>
	<SubTexture name="cool background_gif0319" x="2560" y="1344" width="256" height="224"/>
	<SubTexture name="cool background_gif0320" x="2560" y="1344" width="256" height="224"/>
	<SubTexture name="cool background_gif0321" x="2816" y="1344" width="256" height="224"/>
	<SubTexture name="cool background_gif0322" x="2816" y="1344" width="256" height="224"/>
	<SubTexture name="cool background_gif0323" x="2816" y="1344" width="256" height="224"/>
	<SubTexture name="cool background_gif0324" x="3072" y="1344" width="256" height="224"/>
	<SubTexture name="cool background_gif0325" x="3072" y="1344" width="256" height="224"/>
	<SubTexture name="cool background_gif0326" x="3072" y="1344" width="256" height="224"/>
	<SubTexture name="cool background_gif0327" x="3328" y="1344" width="256" height="224"/>
	<SubTexture name="cool background_gif0328" x="3328" y="1344" width="256" height="224"/>
	<SubTexture name="cool background_gif0329" x="3328" y="1344" width="256" height="224"/>
	<SubTexture name="cool background_gif0330" x="3584" y="1344" width="256" height="224"/>
	<SubTexture name="cool background_gif0331" x="3584" y="1344" width="256" height="224"/>
	<SubTexture name="cool background_gif0332" x="3584" y="1344" width="256" height="224"/>
	<SubTexture name="cool background_gif0333" x="3840" y="1344" width="256" height="224"/>
	<SubTexture name="cool background_gif0334" x="3840" y="1344" width="256" height="224"/>
	<SubTexture name="cool background_gif0335" x="3840" y="1344" width="256" height="224"/>
	<SubTexture name="cool background_gif0336" x="0" y="1568" width="256" height="224"/>
	<SubTexture name="cool background_gif0337" x="0" y="1568" width="256" height="224"/>
	<SubTexture name="cool background_gif0338" x="0" y="1568" width="256" height="224"/>
	<SubTexture name="cool background_gif0339" x="256" y="1568" width="256" height="224"/>
	<SubTexture name="cool background_gif0340" x="256" y="1568" width="256" height="224"/>
	<SubTexture name="cool background_gif0341" x="256" y="1568" width="256" height="224"/>
	<SubTexture name="cool background_gif0342" x="512" y="1568" width="256" height="224"/>
	<SubTexture name="cool background_gif0343" x="512" y="1568" width="256" height="224"/>
	<SubTexture name="cool background_gif0344" x="512" y="1568" width="256" height="224"/>
	<SubTexture name="cool background_gif0345" x="768" y="1568" width="256" height="224"/>
	<SubTexture name="cool background_gif0346" x="768" y="1568" width="256" height="224"/>
	<SubTexture name="cool background_gif0347" x="768" y="1568" width="256" height="224"/>
	<SubTexture name="cool background_gif0348" x="1024" y="1568" width="256" height="224"/>
	<SubTexture name="cool background_gif0349" x="1024" y="1568" width="256" height="224"/>
	<SubTexture name="cool background_gif0350" x="1024" y="1568" width="256" height="224"/>
	<SubTexture name="cool background_gif0351" x="1280" y="1568" width="256" height="224"/>
	<SubTexture name="cool background_gif0352" x="1280" y="1568" width="256" height="224"/>
	<SubTexture name="cool background_gif0353" x="1280" y="1568" width="256" height="224"/>
	<SubTexture name="cool background_gif0354" x="1536" y="1568" width="256" height="224"/>
	<SubTexture name="cool background_gif0355" x="1536" y="1568" width="256" height="224"/>
	<SubTexture name="cool background_gif0356" x="1536" y="1568" width="256" height="224"/>
	<SubTexture name="cool background_gif0357" x="1792" y="1568" width="256" height="224"/>
	<SubTexture name="cool background_gif0358" x="1792" y="1568" width="256" height="224"/>
	<SubTexture name="cool background_gif0359" x="1792" y="1568" width="256" height="224"/>
	<SubTexture name="cool background_gif0360" x="2048" y="1568" width="256" height="224"/>
	<SubTexture name="cool background_gif0361" x="2048" y="1568" width="256" height="224"/>
	<SubTexture name="cool background_gif0362" x="2048" y="1568" width="256" height="224"/>
	<SubTexture name="cool background_gif0363" x="2304" y="1568" width="256" height="224"/>
	<SubTexture name="cool background_gif0364" x="2304" y="1568" width="256" height="224"/>
	<SubTexture name="cool background_gif0365" x="2304" y="1568" width="256" height="224"/>
	<SubTexture name="cool background_gif0366" x="2560" y="1568" width="256" height="224"/>
	<SubTexture name="cool background_gif0367" x="2560" y="1568" width="256" height="224"/>
	<SubTexture name="cool background_gif0368" x="2560" y="1568" width="256" height="224"/>
	<SubTexture name="cool background_gif0369" x="2816" y="1568" width="256" height="224"/>
	<SubTexture name="cool background_gif0370" x="2816" y="1568" width="256" height="224"/>
	<SubTexture name="cool background_gif0371" x="2816" y="1568" width="256" height="224"/>
	<SubTexture name="cool background_gif0372" x="3072" y="1568" width="256" height="224"/>
	<SubTexture name="cool background_gif0373" x="3072" y="1568" width="256" height="224"/>
	<SubTexture name="cool background_gif0374" x="3072" y="1568" width="256" height="224"/>
	<SubTexture name="cool background_gif0375" x="3328" y="1568" width="256" height="224"/>
	<SubTexture name="cool background_gif0376" x="3328" y="1568" width="256" height="224"/>
	<SubTexture name="cool background_gif0377" x="3328" y="1568" width="256" height="224"/>
	<SubTexture name="cool background_gif0378" x="3584" y="1568" width="256" height="224"/>
	<SubTexture name="cool background_gif0379" x="3584" y="1568" width="256" height="224"/>
	<SubTexture name="cool background_gif0380" x="3584" y="1568" width="256" height="224"/>
	<SubTexture name="cool background_gif0381" x="3840" y="1568" width="256" height="224"/>
	<SubTexture name="cool background_gif0382" x="3840" y="1568" width="256" height="224"/>
	<SubTexture name="cool background_gif0383" x="3840" y="1568" width="256" height="224"/>
	<SubTexture name="cool background_gif0384" x="0" y="1792" width="256" height="224"/>
	<SubTexture name="cool background_gif0385" x="0" y="1792" width="256" height="224"/>
	<SubTexture name="cool background_gif0386" x="0" y="1792" width="256" height="224"/>
	<SubTexture name="cool background_gif0387" x="256" y="1792" width="256" height="224"/>
	<SubTexture name="cool background_gif0388" x="256" y="1792" width="256" height="224"/>
	<SubTexture name="cool background_gif0389" x="256" y="1792" width="256" height="224"/>
	<SubTexture name="cool background_gif0390" x="512" y="1792" width="256" height="224"/>
	<SubTexture name="cool background_gif0391" x="512" y="1792" width="256" height="224"/>
	<SubTexture name="cool background_gif0392" x="512" y="1792" width="256" height="224"/>
	<SubTexture name="cool background_gif0393" x="768" y="1792" width="256" height="224"/>
	<SubTexture name="cool background_gif0394" x="768" y="1792" width="256" height="224"/>
	<SubTexture name="cool background_gif0395" x="768" y="1792" width="256" height="224"/>
	<SubTexture name="cool background_gif0396" x="1024" y="1792" width="256" height="224"/>
	<SubTexture name="cool background_gif0397" x="1024" y="1792" width="256" height="224"/>
	<SubTexture name="cool background_gif0398" x="1024" y="1792" width="256" height="224"/>
</TextureAtlas>
